radpy/__.init__.py
radpy/batchmode.py
radpy/config.py
radpy/data/GAIA.GAIA3.G.dat
radpy/data/GAIA.GAIA3.Gbp.dat
radpy/data/GAIA.GAIA3.Grp.dat
radpy/data/Hipparcos.Hipparcos.Hp_MvB.dat
radpy/data/Johnson.H.dat
radpy/data/Johnson.J.dat
radpy/data/Johnson.K.dat
radpy/data/ldcHA.csv
radpy/data/ldcHAF.csv
radpy/data/ldcHP.csv
radpy/data/ldcHPF.csv
radpy/data/ldcJA.csv
radpy/data/ldcJAF.csv
radpy/data/ldcJP.csv
radpy/data/ldcJPF.csv
radpy/data/ldcKA.csv
radpy/data/ldcKAF.csv
radpy/data/ldcKP.csv
radpy/data/ldcKPF.csv
radpy/data/ldcRA.csv
radpy/data/ldcRAF.csv
radpy/data/ldcRP.csv
radpy/data/ldcRPF.csv
radpy/data/Stromgren.b.dat
radpy/data/Stromgren.u.dat
radpy/data/Stromgren.v.dat
radpy/data/Stromgren.y.dat
radpy/data/svo_filter_info.csv
radpy/data/template_photometry_datafile.csv
radpy/data/TESS.TESS.Red.dat
radpy/data/TYCHO.TYCHO.B_MvB.dat
radpy/data/TYCHO.TYCHO.V_MvB.dat
radpy/datareadandformat.py
radpy/LDfitting.py
radpy/limbdarkcoeffs.py
radpy/plotting.py
radpy/process.py
radpy/sed_batch_mode.py
radpy/sedfit.py
radpy/stellar.py
radpy/UDfitting.py
rsadpy-0.12.0.dist-info/licenses/LICENSE
rsadpy-0.12.0.dist-info/METADATA
rsadpy-0.12.0.dist-info/WHEEL
rsadpy-0.12.0.dist-info/RECORD
