Metadata-Version: 2.4
Name: rsadpy
Version: 0.12.0
Summary: Robust Angular Diameters in Python: an angular diameter fitting routine for multi-wavelength interferometric data
License: GPL-3.0
License-File: LICENSE
Keywords: interferometry,angular diameters,CHARA
Author: Ashley Elliott
Author-email: elliottashleya99@gmail.com
Requires-Python: >=3.11
Classifier: License :: OSI Approved :: GNU General Public License v3 (GPLv3)
Classifier: Programming Language :: Python :: 3
Classifier: Programming Language :: Python :: 3.11
Classifier: Programming Language :: Python :: 3.12
Classifier: Programming Language :: Python :: 3.13
Classifier: Programming Language :: Python :: 3.14
Requires-Dist: astropy (>=6.1.6)
Requires-Dist: astroquery (>=0.4.6)
Requires-Dist: corner (>=2.2.2)
Requires-Dist: gaiadr3-zeropoint (>=0.0.4)
Requires-Dist: lmfit (>=1.2.2)
Requires-Dist: matplotlib (>=3.9.2)
Requires-Dist: numpy (>=1.25.2)
Requires-Dist: pandas (>=2.2.2)
Requires-Dist: pint (>=0.25.2)
Requires-Dist: scipy (>=1.10.0)
Requires-Dist: uncertainties (>=3.1.7)
Project-URL: Repository, https://github.com/spaceashley/radpy.git
Project-URL: repository, https://github.com/spaceashley/radpy.git
